[
  {
    "author": "Vitor",
    "code": "/**\n * @param {number[][]} queries\n * @return {boolean[]}\n */\nvar getResults = function(queries) {\n    let intervals = [[0, Infinity]];\n    const res = [];\n\n    const binSearch = (target) => {\n        let left = 0;\n        let right = intervals.length - 1;\n\n        while (left < right) {\n            const mid = Math.floor((left + right) / 2);\n\n            if (intervals[mid][1] < target) {\n                left = mid + 1;\n            } else {\n                right = mid;\n            }\n        }\n\n        return left;\n    };\n\n    for (const query of queries) {\n        if (query[0] === 1) {\n            const x = query[1];\n\n            const pos = binSearch(x);\n            const [s, e] = intervals[pos];\n\n            intervals[pos] = [s, x];\n            intervals.splice(pos + 1, 0, [x, e]);\n        } else {\n            const x = query[1];\n            const sz = query[2];\n\n            let canAdd = false;\n\n            for (let i = 0; i < intervals.length; i++) {\n                if (intervals[i][0] > x) {\n                    break;\n                }\n\n                if (Math.min(intervals[i][1], x) - intervals[i][0] >= sz) {\n                    canAdd = true;\n                    break;\n                }\n            }\n\n            res.push(canAdd);\n        }\n    }\n\n    return res;\n};",
    "language": "javascript",
    "explanation": "Keep track of the intervals in a sorted array. For each query, if it is a build query, add a new interval to the array. Otherwise, check if any interval intersects with the query. Use binary search to find the position of the interval that intersects with the query.",
    "status": "TLE",
    "cpuUsage": 0,
    "memoryUsage": 0,
    "explanationSource": "AI"
  },
  {
    "author": "Leetcode",
    "code": "/**\n * @param {number[][]} queries\n * @return {boolean[]}\n */\nvar getResults = function (queries) {\n    const mx = 50000;\n    const st = [0, mx];\n\n    const bisectLeft = (arr, x) => {\n        let lo = 0,\n            hi = arr.length;\n        while (lo < hi) {\n            const mid = (lo + hi) >>> 1;\n            if (arr[mid] < x) lo = mid + 1;\n            else hi = mid;\n        }\n        return lo;\n    };\n\n    const insort = (arr, x) => {\n        const idx = bisectLeft(arr, x);\n        arr.splice(idx, 0, x);\n    };\n\n    for (const q of queries) {\n        if (q[0] === 1) {\n            insort(st, q[1]);\n        }\n    }\n\n    const bt = new Array(mx + 1).fill(0);\n\n    const update = (x, v) => {\n        while (x <= mx) {\n            if (v > bt[x]) bt[x] = v;\n            x += x & -x;\n        }\n    };\n\n    const query = (x) => {\n        let res = 0;\n        while (x > 0) {\n            if (bt[x] > res) res = bt[x];\n            x -= x & -x;\n        }\n        return res;\n    };\n\n    let pre = 0;\n    for (const x of st) {\n        if (x === 0) {\n            continue;\n        }\n        update(x, x - pre);\n        pre = x;\n    }\n\n    const ans = [];\n    for (let i = queries.length - 1; i >= 0; i--) {\n        const q = queries[i];\n        if (q[0] === 2) {\n            const x = q[1],\n                sz = q[2];\n            const idx = bisectLeft(st, x);\n            let preVal;\n\n            if (idx < st.length && st[idx] === x) {\n                preVal = x;\n            } else {\n                preVal = st[idx - 1];\n            }\n\n            let maxSpace = query(preVal);\n            maxSpace = Math.max(maxSpace, x - preVal);\n            ans.push(maxSpace >= sz);\n        } else {\n            const x = q[1];\n            const idx = bisectLeft(st, x);\n            const preVal = st[idx - 1];\n            const nxt = st[idx + 1];\n\n            update(nxt, nxt - preVal);\n            st.splice(idx, 1);\n        }\n    }\n\n    return ans.reverse();\n};",
    "language": "javascript",
    "explanation": "Initially, we assume that all obstacles already exist. Then, while traversing the queries backward, we remove obstacles one by one, causing adjacent intervals to merge into larger intervals.\n\nLet d[r] denote the distance from r to the nearest obstacle on its left. Let pre and nxt represent the positions of the nearest obstacles to the left and right of x, respectively. Then:\n\nd[r]=r\u2212pre\n\nWhen deleting an obstacle at position x, the two original intervals [pre,x] and [x,nxt] merge into a single interval [pre,nxt], whose length becomes:\n\nnxt\u2212pre\n\nSince interval lengths only increase during this reverse process, we can use a Fenwick tree to maintain prefix maximums efficiently.",
    "explanationSource": "AI",
    "status": "DONE",
    "cpuUsage": 28.57,
    "memoryUsage": 57.14
  }
]